RISC_V/control_unit.sv
module control_unit (
    input logic [6:0] opcode, funct7,
    input logic [2:0] funct3, 
    input logic zero, 
    output logic PCSrc, ResultSrc, MemWrite, ALUSrc, RegWrite,
    output logic [2:0] ALUControl,
    output logic [1:0] ImmSrc
);

    logic [1:0] ALUopcode;
    logic Branch;
    logic opcode_5, funct7_5;

    assign opcode_5 = opcode[5]; // sixth bit 
    assign funct7_5 = funct7[5]; //sixth bit
    assign PCSrc = Branch & zero;

    always_comb begin
        case (opcode)
            // lw (load word)
            7'b0000011 : begin
                RegWrite = 1;
                ImmSrc = 2'b00;
                ALUSrc = 1;
                MemWrite = 0;
                ResultSrc = 1; 
                Branch = 0;
                ALUopcode = 2'b00;
            end

            // sw (store word)
            7'b0100011 : begin
                RegWrite = 0;
                ImmSrc = 2'b01; 
                ALUSrc = 1;
                MemWrite = 1;
                ResultSrc = 0; 
                Branch = 0;
                ALUopcode = 2'b00;
            end
            
            // R-type (register to register operation)
            7'b0110011 : begin
                RegWrite = 1;
                ImmSrc = 2'b00; 
                ALUSrc = 0;
                MemWrite = 0;
                ResultSrc = 0;
                Branch = 0;
                ALUopcode = 2'b10;
            end

            // beq (branch equal)
                7'b1100011 : begin
                RegWrite = 0;
                ImmSrc = 2'b10;
                ALUSrc = 0;
                MemWrite = 0;
                ResultSrc = 0;
                Branch = 1;
                ALUopcode = 2'b01;
            end

            // I-type (short immediate or load operation)
            7'b0010011 : begin
                RegWrite = 1;
                ImmSrc = 2'b00;
                ALUSrc = 1;
                MemWrite = 0;
                ResultSrc = 0;
                Branch = 0;
                ALUopcode = 2'b10;
            end

            default : begin
                RegWrite = 1'bx;
                ImmSrc = 2'bxx;
                ALUSrc = 2'bxx;
                MemWrite = 1'bx;
                ResultSrc = 2'bxx;
                Branch = 1'bx;
                ALUopcode = 2'bxx;
            end
        endcase
    end

    always_comb begin
        casex ({ALUopcode,funct3,opcode_5,funct7_5}) 
            7'b00xxxxx : ALUControl = 3'b000; // lw,sw
            7'b01xxxxx : ALUControl = 3'b001; // beq
            7'b1000000 : ALUControl = 3'b000; // add
            7'b1000001 : ALUControl = 3'b000; // add
            7'b1000010 : ALUControl = 3'b000; // add
            7'b1000011 : ALUControl = 3'b001; // sub
            7'b1001000 : ALUControl = 3'b101; // slt
            7'b1011000 : ALUControl = 3'b011; // or
            7'b1011100 : ALUControl = 3'b010; // and
            default : ALUControl = 3'b111;    // default : ALUControl = 3'bxxx;
        endcase
    end
endmodule

RISC_V/control_unit_tb.sv
`timescale 1ns/1ps
`include "control_unit.sv"

module control_unit_tb;
    logic [6:0] opcode, funct7;
    logic [2:0] funct3;
    logic zero; 
    logic PCSrc, ResultSrc, MemWrite, ALUSrc, RegWrite;
    logic [2:0] ALUControl;
    logic [1:0] ImmSrc;
    control_unit dut (opcode, funct7, funct3, zero, PCSrc, ResultSrc, MemWrite, ALUSrc, RegWrite, ALUControl, ImmSrc);

    initial begin // Apply stimulus
        $dumpfile("control_unit_tb.vcd");
        $dumpvars(0, control_unit_tb);
        zero = 0; opcode = 7'b0; funct3 = 3'b0; funct7 = 7'b0;
        #10 opcode = 7'b0000011; funct3 = 3'b000; funct7 = 7'b0000000; 
        #10 opcode = 7'b0100011; funct3 = 3'b000; funct7 = 7'b0000000;
        #10 opcode = 7'b0010011; funct3 = 3'b111; funct7 = 7'b0000000;
        #10 opcode = 7'b1100011; funct3 = 3'b010; funct7 = 7'b0000000;//beq
        #10 opcode = 7'b0000011; funct3 = 3'b010; funct7 = 7'b0000000;
        #10 opcode = 7'b1101111; funct3 = 3'b111; funct7 = 7'b0000000;
        #10 opcode = 7'b1100011; funct3 = 3'b000; funct7 = 7'b0000000; zero = 1;
        #30;
        $finish; 
    end

    initial begin
        $monitor ("t = %3d, zero = %b, opcode = %b, funct3 = %b funct7 = %b,RegWrite = %b, ImmSrc = %b, ALUSrc = %b, MemWrite = %b, ResultSrc = %b, ALUControl = %b, PCSrc = %b, ALUOpcode = %b, opcode_5 = %b, funct7_5 = %b", $time, zero, opcode, funct3, funct7, RegWrite, ImmSrc, ALUSrc, MemWrite, ResultSrc, ALUControl, PCSrc, dut.ALUopcode, dut.opcode_5, dut.funct7_5);
    end
endmodule

RISC_V/control_unit_tb.vcd
$date
	Tue Dec 10 06:28:43 2024
$end
$version
	Icarus Verilog
$end
$timescale
	1ps
$end
$scope module control_unit_tb $end
$var wire 1 ! ResultSrc $end
$var wire 1 " RegWrite $end
$var wire 1 # PCSrc $end
$var wire 1 $ MemWrite $end
$var wire 2 % ImmSrc [1:0] $end
$var wire 1 & ALUSrc $end
$var wire 3 ' ALUControl [2:0] $end
$var reg 3 ( funct3 [2:0] $end
$var reg 7 ) funct7 [6:0] $end
$var reg 7 * opcode [6:0] $end
$var reg 1 + zero $end
$scope module dut $end
$var wire 1 # PCSrc $end
$var wire 3 , funct3 [2:0] $end
$var wire 7 - funct7 [6:0] $end
$var wire 7 . opcode [6:0] $end
$var wire 1 + zero $end
$var wire 1 / opcode_5 $end
$var wire 1 0 funct7_5 $end
$var reg 3 1 ALUControl [2:0] $end
$var reg 1 & ALUSrc $end
$var reg 2 2 ALUopcode [1:0] $end
$var reg 1 3 Branch $end
$var reg 2 4 ImmSrc [1:0] $end
$var reg 1 $ MemWrite $end
$var reg 1 " RegWrite $end
$var reg 1 ! ResultSrc $end
$upscope $end
$upscope $end
$enddefinitions $end
$comment Show the parameter values. $end
$dumpall
$end
#0
$dumpvars
bx 4
x3
bx 2
b0 1
00
0/
b0 .
b0 -
b0 ,
0+
b0 *
b0 )
b0 (
b0 '
x&
bx %
x$
0#
x"
x!
$end
#10000
b0 2
03
1!
0$
1&
b0 %
b0 4
1"
b11 *
b11 .
#20000
0!
1$
b1 %
b1 4
0"
1/
b100011 *
b100011 .
#30000
b10 '
b10 1
b10 2
0$
b0 %
b0 4
1"
0/
b111 (
b111 ,
b10011 *
b10011 .
#40000
b1 '
b1 1
b1 2
13
0&
b10 %
b10 4
0"
1/
b10 (
b10 ,
b1100011 *
b1100011 .
#50000
b0 '
b0 1
b0 2
03
1!
1&
b0 %
b0 4
1"
0/
b11 *
b11 .
#60000
bx 2
x3
x!
x$
x&
bx %
bx 4
x"
1/
b111 (
b111 ,
b1101111 *
b1101111 .
#70000
1#
b1 '
b1 1
b1 2
13
0!
0$
0&
b10 %
b10 4
0"
1+
b0 (
b0 ,
b1100011 *
b1100011 .
