RISC_V/program_counter.sv
module program_counter(input logic[31:0] PCTarget,
          input logic PCSrc,clk,reset,
          output logic[31:0] program_counter);

always_ff @ (posedge clk) begin
if (reset) program_counter <= 32'b0; // when reset=1, PC is 0
else if (PCSrc) // In the condition of reset is 0, when PCSrc=1, PC=PCTarget
    program_counter <= PCTarget;
else program_counter <= program_counter + 4; //if PCSrc is 0, PC is the output after counter which is PC+4
end

endmodule

RISC_V/program_counter_tb.sv
`timescale 1ns/1ps
`include "program_counter.sv"

module program_counter_tb;
    logic[31:0] PCTarget;
    logic PCSrc, clk, reset;
    logic[31:0] program_counter;

    // Instantiate the Unit Under Test (UUT)
    program_counter dut (PCTarget, PCSrc, clk, reset, program_counter);

    // Clock signal generation with a period of 10 ns
    initial begin
        clk = 0;
        forever #10 clk = ~clk; // Toggle clock every 10 ns
    end

    // Apply test stimulus
    initial begin
        $dumpfile("program_counter_tb.vcd"); // Create a VCD file for waveform analysis
        $dumpvars(0, program_counter_tb);    // Dump all variables in the test bench

        // Initial values
        reset = 1; // Start with the reset active
        PCSrc = 0; 
        PCTarget = 32'b0; // Initialize the PC target
        #20; reset = 0; PCSrc = 1; PCTarget = 32'h0000000A; // Deassert reset after two clock cycles
        #20; PCSrc = 0;
        #100;
        $finish;
    end

    // Response monitor
    initial begin
    $monitor("Time = %3d, PCTarget = %d, PCSrc = %b, clk = %b, reset = %b, PC = %d", $time, 
             PCTarget, PCSrc, clk, reset, program_counter);
    end

endmodule

RISC_V/program_counter_tb.vcd
$date
	Wed Dec 11 11:16:29 2024
$end
$version
	Icarus Verilog
$end
$timescale
	1ps
$end
$scope module program_counter_tb $end
$var wire 32 ! program_counter [31:0] $end
$var reg 1 " PCSrc $end
$var reg 32 # PCTarget [31:0] $end
$var reg 1 $ clk $end
$var reg 1 % reset $end
$scope module dut $end
$var wire 1 " PCSrc $end
$var wire 32 & PCTarget [31:0] $end
$var wire 1 $ clk $end
$var wire 1 % reset $end
$var reg 32 ' program_counter [31:0] $end
$upscope $end
$upscope $end
$enddefinitions $end
$comment Show the parameter values. $end
$dumpall
$end
#0
$dumpvars
bx '
b0 &
1%
0$
b0 #
0"
bx !
$end
#10000
b0 !
b0 '
1$
#20000
0$
b1010 #
b1010 &
1"
0%
#30000
b1010 !
b1010 '
1$
#40000
0$
0"
#50000
b1110 !
b1110 '
1$
#60000
0$
#70000
b10010 !
b10010 '
1$
#80000
0$
#90000
b10110 !
b10110 '
1$
#100000
0$
#110000
b11010 !
b11010 '
1$
#120000
0$
#130000
b11110 !
b11110 '
1$
